pydnsxone/__init__.py
pydnsxone/dnsxone.py
pydnsxone/request.py
pydnsxone-0.0.4.dist-info/METADATA
pydnsxone-0.0.4.dist-info/WHEEL
pydnsxone-0.0.4.dist-info/top_level.txt
pydnsxone-0.0.4.dist-info/RECORD
